{

  "pageTitle": "TP Node.js",
  "repository": "https://github.com/Romakita/tp-nodejs/",
  "branch": "master",

  "copy": [
    {"from": "${baseDir}/src", "to": "src"}
  ],

  "checkout": {
    "cwd": "../../Resources",
    "branchs": [
      "tp1-installation",
      "tp2-provided",
      "tp2-solution",
      "tp3-installation-provided",
      "tp3-installation-solution",
      "tp3-exercice-solution",
      "tp4-exercice-4-solution",
      "tp4-installation-provided",
      "tp4-installation-solution",
      "tp5-provided",
      "tp6-provided"
    ]
  },

  "pdfName": "labs.pdf",

  "outDir": [
    {"format": "html",  "path": "Instructor/html"},
    {"format": "pdf",  "path": "Instructor/pdf"},
    {"format": "html",  "path": "Student/html"},
    {"format": "pdf",  "path": "Student/pdf"}
  ],

  "concat": {
    "files": [
      {"title": "Accueil", "path": "readme.md"},
      {"title": "TP1 - Installation", "path": "tp1-installation.md"},
      {"title": "TP2 - Manipulation des fichiers", "path": "tp2-fs.md"},
      {"title": "TP3 - Express", "path": "tp3-express.md"},
      {"title": "TP4 - Templating avec EJS", "path": "tp4-express-ejs.md"},
      {"title": "TP5 - Middlewares, Formulaire & Services", "path": "tp5-express-middlewares-form-services.md"},
      {"title": "TP6 - Socket.io", "path": "tp6-socketio.md"},
      {"title": "TP7 - Les promises", "path": "tp7-promise.md"},
      {"title": "TP8 - Base de données", "path": "tp8-mongoose.md"},
      {"title": "TP9 - Test unitaires", "path": "tp9-test-unitaires.md"},
      {"title": "Aide - importation des modules", "path": "aide-importation-module.md"}
    ]
  }
}